zoviz/__init__.py
zoviz/database.py
zoviz/metadata.py
zoviz/visualization.py
zoviz-0.4.292.dist-info/LICENSE
zoviz-0.4.292.dist-info/METADATA
zoviz-0.4.292.dist-info/WHEEL
zoviz-0.4.292.dist-info/top_level.txt
zoviz-0.4.292.dist-info/RECORD
