Metadata-Version: 2.1
Name: zoviz
Version: 0.4.292
Summary: Unaffiliated visualization helper for Zotero data
Home-page: https://gitlab.com/jlogan03/zoviz
Author: James Logan
Author-email: jlogan03@gmail.com
Classifier: Programming Language :: Python :: 3
Classifier: License :: OSI Approved :: MIT License
Classifier: Operating System :: OS Independent
Requires-Python: >=3.5
License-File: LICENSE
Requires-Dist: matplotlib
Requires-Dist: networkx
Requires-Dist: seaborn
Requires-Dist: pandas
